AddGithubMembers.py
CreateGithubTeamRepos.py
DuplicateGithubRepos.py
LICENSE.txt
ListGithubCollab.py
README.md
pyproject.toml
setup.cfg
setup.py
pygithubutils/__init__.py
pygithubutils/base.py
pygithubutils/duplicator.py
pygithubutils/get.py
pygithubutils/repo_stats.py
pygithubutils.egg-info/PKG-INFO
pygithubutils.egg-info/SOURCES.txt
pygithubutils.egg-info/dependency_links.txt
pygithubutils.egg-info/not-zip-safe
pygithubutils.egg-info/requires.txt
pygithubutils.egg-info/top_level.txt