Metadata-Version: 2.1
Name: pygithubutils
Version: 1.0.2
Summary: Manage large 1..1000 user teams for classroom and insitutions with GitHub API calls.
Home-page: https://github.com/scivision/pygithub-utils
Author: Michael Hirsch, Ph.D.
Author-email: scivision@users.noreply.github.com
License: UNKNOWN
Keywords: git,GitHub
Platform: UNKNOWN
Classifier: Development Status :: 5 - Production/Stable
Classifier: Environment :: Console
Classifier: Intended Audience :: Developers
Classifier: Operating System :: OS Independent
Classifier: Programming Language :: Python :: 3.6
Classifier: Programming Language :: Python :: 3.7
Classifier: Programming Language :: Python :: 3.8
Classifier: Programming Language :: Python :: 3.9
Classifier: Topic :: Software Development :: Version Control :: Git
Classifier: Topic :: Utilities
Requires-Python: >=3.6
Provides-Extra: tests
Provides-Extra: lint
